[
  {
    "ContainingType": "Converted_POS.FunctionController",
    "Method": "SelectAll",
    "RelativePath": "api/Function",
    "HttpMethod": "",
    "IsController": true,
    "Order": 0,
    "Parameters": [
      {
        "Name": "c_id",
        "Type": "System.Nullable\u00601[[System.Int32, System.Private.CoreLib, Version=9.0.0.0, Culture=neutral, PublicKeyToken=7cec85d7bea7798e]]",
        "IsRequired": false
      },
      {
        "Name": "conn",
        "Type": "System.String",
        "IsRequired": false
      }
    ],
    "ReturnTypes": [
      {
        "Type": "System.Collections.Generic.IEnumerable\u00601[[Converted_POS.Models.clsFunction, Converted_POS, Version=1.0.0.0, Culture=neutral, PublicKeyToken=null]]",
        "MediaTypes": [
          "text/plain",
          "application/json",
          "text/json"
        ],
        "StatusCode": 200
      }
    ]
  },
  {
    "ContainingType": "Converted_POS.FunctionController",
    "Method": "Select",
    "RelativePath": "api/Function",
    "HttpMethod": "",
    "IsController": true,
    "Order": 0,
    "Parameters": [
      {
        "Name": "mainfunction_id",
        "Type": "System.Int32",
        "IsRequired": false
      },
      {
        "Name": "cmpId",
        "Type": "System.Int32",
        "IsRequired": false
      },
      {
        "Name": "connStr",
        "Type": "System.String",
        "IsRequired": false
      }
    ],
    "ReturnTypes": [
      {
        "Type": "Converted_POS.Models.clsFunction",
        "MediaTypes": [
          "text/plain",
          "application/json",
          "text/json"
        ],
        "StatusCode": 200
      }
    ]
  },
  {
    "ContainingType": "Converted_POS.FunctionController",
    "Method": "BindSwapMachineFunction",
    "RelativePath": "api/Function",
    "HttpMethod": "",
    "IsController": true,
    "Order": 0,
    "Parameters": [
      {
        "Name": "id",
        "Type": "System.Int32",
        "IsRequired": false
      },
      {
        "Name": "c_id",
        "Type": "System.Nullable\u00601[[System.Int32, System.Private.CoreLib, Version=9.0.0.0, Culture=neutral, PublicKeyToken=7cec85d7bea7798e]]",
        "IsRequired": false
      },
      {
        "Name": "conn",
        "Type": "System.String",
        "IsRequired": false
      }
    ],
    "ReturnTypes": [
      {
        "Type": "System.Data.DataTable",
        "MediaTypes": [
          "text/plain",
          "application/json",
          "text/json"
        ],
        "StatusCode": 200
      }
    ]
  },
  {
    "ContainingType": "Converted_POS.FunctionController",
    "Method": "SelectPanelFunction",
    "RelativePath": "api/Function",
    "HttpMethod": "",
    "IsController": true,
    "Order": 0,
    "Parameters": [
      {
        "Name": "panelID",
        "Type": "System.Int32",
        "IsRequired": false
      },
      {
        "Name": "id",
        "Type": "System.Int32",
        "IsRequired": false
      },
      {
        "Name": "c_id",
        "Type": "System.Nullable\u00601[[System.Int32, System.Private.CoreLib, Version=9.0.0.0, Culture=neutral, PublicKeyToken=7cec85d7bea7798e]]",
        "IsRequired": false
      },
      {
        "Name": "conn",
        "Type": "System.String",
        "IsRequired": false
      }
    ],
    "ReturnTypes": [
      {
        "Type": "System.Data.DataTable",
        "MediaTypes": [
          "text/plain",
          "application/json",
          "text/json"
        ],
        "StatusCode": 200
      }
    ]
  },
  {
    "ContainingType": "Converted_POS.FunctionController",
    "Method": "SelectFunction_Details",
    "RelativePath": "api/Function",
    "HttpMethod": "",
    "IsController": true,
    "Order": 0,
    "Parameters": [
      {
        "Name": "id",
        "Type": "System.Int32",
        "IsRequired": false
      },
      {
        "Name": "c_id",
        "Type": "System.Nullable\u00601[[System.Int32, System.Private.CoreLib, Version=9.0.0.0, Culture=neutral, PublicKeyToken=7cec85d7bea7798e]]",
        "IsRequired": false
      },
      {
        "Name": "conn",
        "Type": "System.String",
        "IsRequired": false
      }
    ],
    "ReturnTypes": [
      {
        "Type": "System.Data.DataTable",
        "MediaTypes": [
          "text/plain",
          "application/json",
          "text/json"
        ],
        "StatusCode": 200
      }
    ]
  },
  {
    "ContainingType": "Converted_POS.FunctionController",
    "Method": "BindFunctionSwap",
    "RelativePath": "api/Function",
    "HttpMethod": "",
    "IsController": true,
    "Order": 0,
    "Parameters": [
      {
        "Name": "c_id",
        "Type": "System.Nullable\u00601[[System.Int32, System.Private.CoreLib, Version=9.0.0.0, Culture=neutral, PublicKeyToken=7cec85d7bea7798e]]",
        "IsRequired": false
      },
      {
        "Name": "id",
        "Type": "System.Int32",
        "IsRequired": false
      },
      {
        "Name": "conn",
        "Type": "System.String",
        "IsRequired": false
      }
    ],
    "ReturnTypes": [
      {
        "Type": "System.Data.DataTable",
        "MediaTypes": [
          "text/plain",
          "application/json",
          "text/json"
        ],
        "StatusCode": 200
      }
    ]
  },
  {
    "ContainingType": "Converted_POS.FunctionController",
    "Method": "GetMachine",
    "RelativePath": "api/Function",
    "HttpMethod": "",
    "IsController": true,
    "Order": 0,
    "Parameters": [
      {
        "Name": "c_id",
        "Type": "System.Nullable\u00601[[System.Int32, System.Private.CoreLib, Version=9.0.0.0, Culture=neutral, PublicKeyToken=7cec85d7bea7798e]]",
        "IsRequired": false
      },
      {
        "Name": "conn",
        "Type": "System.String",
        "IsRequired": false
      },
      {
        "Name": "MachineID",
        "Type": "System.Int32",
        "IsRequired": false
      }
    ],
    "ReturnTypes": [
      {
        "Type": "System.Collections.Generic.List\u00601[[Microsoft.AspNetCore.Mvc.Rendering.SelectListItem, Microsoft.AspNetCore.Mvc.ViewFeatures, Version=9.0.0.0, Culture=neutral, PublicKeyToken=adb9793829ddae60]]",
        "MediaTypes": [
          "text/plain",
          "application/json",
          "text/json"
        ],
        "StatusCode": 200
      }
    ]
  },
  {
    "ContainingType": "Converted_POS.FunctionController",
    "Method": "GetTax",
    "RelativePath": "api/Function",
    "HttpMethod": "",
    "IsController": true,
    "Order": 0,
    "Parameters": [
      {
        "Name": "c_id",
        "Type": "System.Nullable\u00601[[System.Int32, System.Private.CoreLib, Version=9.0.0.0, Culture=neutral, PublicKeyToken=7cec85d7bea7798e]]",
        "IsRequired": false
      },
      {
        "Name": "conn",
        "Type": "System.String",
        "IsRequired": false
      }
    ],
    "ReturnTypes": [
      {
        "Type": "System.Collections.Generic.List\u00601[[Microsoft.AspNetCore.Mvc.Rendering.SelectListItem, Microsoft.AspNetCore.Mvc.ViewFeatures, Version=9.0.0.0, Culture=neutral, PublicKeyToken=adb9793829ddae60]]",
        "MediaTypes": [
          "text/plain",
          "application/json",
          "text/json"
        ],
        "StatusCode": 200
      }
    ]
  },
  {
    "ContainingType": "Converted_POS.FunctionController",
    "Method": "GetTill",
    "RelativePath": "api/Function",
    "HttpMethod": "",
    "IsController": true,
    "Order": 0,
    "Parameters": [
      {
        "Name": "c_id",
        "Type": "System.Nullable\u00601[[System.Int32, System.Private.CoreLib, Version=9.0.0.0, Culture=neutral, PublicKeyToken=7cec85d7bea7798e]]",
        "IsRequired": false
      },
      {
        "Name": "conn",
        "Type": "System.String",
        "IsRequired": false
      },
      {
        "Name": "TmachineID",
        "Type": "System.Nullable\u00601[[System.Int32, System.Private.CoreLib, Version=9.0.0.0, Culture=neutral, PublicKeyToken=7cec85d7bea7798e]]",
        "IsRequired": false
      }
    ],
    "ReturnTypes": [
      {
        "Type": "System.Collections.Generic.List\u00601[[Microsoft.AspNetCore.Mvc.Rendering.SelectListItem, Microsoft.AspNetCore.Mvc.ViewFeatures, Version=9.0.0.0, Culture=neutral, PublicKeyToken=adb9793829ddae60]]",
        "MediaTypes": [
          "text/plain",
          "application/json",
          "text/json"
        ],
        "StatusCode": 200
      }
    ]
  },
  {
    "ContainingType": "Converted_POS.FunctionController",
    "Method": "SelectEditPanelByCmp",
    "RelativePath": "api/Function",
    "HttpMethod": "",
    "IsController": true,
    "Order": 0,
    "Parameters": [
      {
        "Name": "c_id",
        "Type": "System.Nullable\u00601[[System.Int32, System.Private.CoreLib, Version=9.0.0.0, Culture=neutral, PublicKeyToken=7cec85d7bea7798e]]",
        "IsRequired": false
      },
      {
        "Name": "mainfunction_id",
        "Type": "System.Int32",
        "IsRequired": false
      },
      {
        "Name": "conn",
        "Type": "System.String",
        "IsRequired": false
      }
    ],
    "ReturnTypes": [
      {
        "Type": "System.Collections.Generic.List\u00601[[Microsoft.AspNetCore.Mvc.Rendering.SelectListItem, Microsoft.AspNetCore.Mvc.ViewFeatures, Version=9.0.0.0, Culture=neutral, PublicKeyToken=adb9793829ddae60]]",
        "MediaTypes": [
          "text/plain",
          "application/json",
          "text/json"
        ],
        "StatusCode": 200
      }
    ]
  },
  {
    "ContainingType": "Converted_POS.FunctionController",
    "Method": "SelectParentFunctionByCmp",
    "RelativePath": "api/Function",
    "HttpMethod": "",
    "IsController": true,
    "Order": 0,
    "Parameters": [
      {
        "Name": "c_id",
        "Type": "System.Nullable\u00601[[System.Int32, System.Private.CoreLib, Version=9.0.0.0, Culture=neutral, PublicKeyToken=7cec85d7bea7798e]]",
        "IsRequired": false
      },
      {
        "Name": "conn",
        "Type": "System.String",
        "IsRequired": false
      }
    ],
    "ReturnTypes": [
      {
        "Type": "System.Collections.Generic.List\u00601[[Microsoft.AspNetCore.Mvc.Rendering.SelectListItem, Microsoft.AspNetCore.Mvc.ViewFeatures, Version=9.0.0.0, Culture=neutral, PublicKeyToken=adb9793829ddae60]]",
        "MediaTypes": [
          "text/plain",
          "application/json",
          "text/json"
        ],
        "StatusCode": 200
      }
    ]
  },
  {
    "ContainingType": "Converted_POS.FunctionController",
    "Method": "SelectFunctionByCmp",
    "RelativePath": "api/Function",
    "HttpMethod": "",
    "IsController": true,
    "Order": 0,
    "Parameters": [
      {
        "Name": "c_id",
        "Type": "System.Nullable\u00601[[System.Int32, System.Private.CoreLib, Version=9.0.0.0, Culture=neutral, PublicKeyToken=7cec85d7bea7798e]]",
        "IsRequired": false
      },
      {
        "Name": "conn",
        "Type": "System.String",
        "IsRequired": false
      }
    ],
    "ReturnTypes": [
      {
        "Type": "System.Collections.Generic.List\u00601[[Microsoft.AspNetCore.Mvc.Rendering.SelectListItem, Microsoft.AspNetCore.Mvc.ViewFeatures, Version=9.0.0.0, Culture=neutral, PublicKeyToken=adb9793829ddae60]]",
        "MediaTypes": [
          "text/plain",
          "application/json",
          "text/json"
        ],
        "StatusCode": 200
      }
    ]
  },
  {
    "ContainingType": "Converted_POS.FunctionController",
    "Method": "SelectPayment",
    "RelativePath": "api/Function",
    "HttpMethod": "",
    "IsController": true,
    "Order": 0,
    "Parameters": [
      {
        "Name": "c_id",
        "Type": "System.Nullable\u00601[[System.Int32, System.Private.CoreLib, Version=9.0.0.0, Culture=neutral, PublicKeyToken=7cec85d7bea7798e]]",
        "IsRequired": false
      },
      {
        "Name": "conn",
        "Type": "System.String",
        "IsRequired": false
      }
    ],
    "ReturnTypes": [
      {
        "Type": "System.Collections.Generic.List\u00601[[Microsoft.AspNetCore.Mvc.Rendering.SelectListItem, Microsoft.AspNetCore.Mvc.ViewFeatures, Version=9.0.0.0, Culture=neutral, PublicKeyToken=adb9793829ddae60]]",
        "MediaTypes": [
          "text/plain",
          "application/json",
          "text/json"
        ],
        "StatusCode": 200
      }
    ]
  },
  {
    "ContainingType": "Converted_POS.FunctionController",
    "Method": "SelectLocation",
    "RelativePath": "api/Function",
    "HttpMethod": "",
    "IsController": true,
    "Order": 0,
    "Parameters": [
      {
        "Name": "c_id",
        "Type": "System.Nullable\u00601[[System.Int32, System.Private.CoreLib, Version=9.0.0.0, Culture=neutral, PublicKeyToken=7cec85d7bea7798e]]",
        "IsRequired": false
      },
      {
        "Name": "venue_id",
        "Type": "System.Nullable\u00601[[System.Int32, System.Private.CoreLib, Version=9.0.0.0, Culture=neutral, PublicKeyToken=7cec85d7bea7798e]]",
        "IsRequired": false
      },
      {
        "Name": "conn",
        "Type": "System.String",
        "IsRequired": false
      }
    ],
    "ReturnTypes": [
      {
        "Type": "System.Collections.Generic.List\u00601[[Microsoft.AspNetCore.Mvc.Rendering.SelectListItem, Microsoft.AspNetCore.Mvc.ViewFeatures, Version=9.0.0.0, Culture=neutral, PublicKeyToken=adb9793829ddae60]]",
        "MediaTypes": [
          "text/plain",
          "application/json",
          "text/json"
        ],
        "StatusCode": 200
      }
    ]
  },
  {
    "ContainingType": "Converted_POS.FunctionController",
    "Method": "SelectVenueByCmp",
    "RelativePath": "api/Function",
    "HttpMethod": "",
    "IsController": true,
    "Order": 0,
    "Parameters": [
      {
        "Name": "c_id",
        "Type": "System.Nullable\u00601[[System.Int32, System.Private.CoreLib, Version=9.0.0.0, Culture=neutral, PublicKeyToken=7cec85d7bea7798e]]",
        "IsRequired": false
      },
      {
        "Name": "conn",
        "Type": "System.String",
        "IsRequired": false
      }
    ],
    "ReturnTypes": [
      {
        "Type": "System.Collections.Generic.List\u00601[[Microsoft.AspNetCore.Mvc.Rendering.SelectListItem, Microsoft.AspNetCore.Mvc.ViewFeatures, Version=9.0.0.0, Culture=neutral, PublicKeyToken=adb9793829ddae60]]",
        "MediaTypes": [
          "text/plain",
          "application/json",
          "text/json"
        ],
        "StatusCode": 200
      }
    ]
  },
  {
    "ContainingType": "Converted_POS.FunctionController",
    "Method": "SelectCardPaymentTyp",
    "RelativePath": "api/Function",
    "HttpMethod": "",
    "IsController": true,
    "Order": 0,
    "Parameters": [
      {
        "Name": "c_id",
        "Type": "System.Nullable\u00601[[System.Int32, System.Private.CoreLib, Version=9.0.0.0, Culture=neutral, PublicKeyToken=7cec85d7bea7798e]]",
        "IsRequired": false
      },
      {
        "Name": "conn",
        "Type": "System.String",
        "IsRequired": false
      }
    ],
    "ReturnTypes": [
      {
        "Type": "System.Collections.Generic.List\u00601[[Microsoft.AspNetCore.Mvc.Rendering.SelectListItem, Microsoft.AspNetCore.Mvc.ViewFeatures, Version=9.0.0.0, Culture=neutral, PublicKeyToken=adb9793829ddae60]]",
        "MediaTypes": [
          "text/plain",
          "application/json",
          "text/json"
        ],
        "StatusCode": 200
      }
    ]
  },
  {
    "ContainingType": "Converted_POS.FunctionController",
    "Method": "Delete",
    "RelativePath": "api/Function",
    "HttpMethod": "POST",
    "IsController": true,
    "Order": 0,
    "Parameters": [
      {
        "Name": "func",
        "Type": "Converted_POS.Models.clsFunction",
        "IsRequired": true
      },
      {
        "Name": "connStr",
        "Type": "System.String",
        "IsRequired": false
      }
    ],
    "ReturnTypes": []
  },
  {
    "ContainingType": "Converted_POS.FunctionController",
    "Method": "Insert",
    "RelativePath": "api/Function",
    "HttpMethod": "",
    "IsController": true,
    "Order": 0,
    "Parameters": [
      {
        "Name": "func",
        "Type": "Converted_POS.Models.clsFunction",
        "IsRequired": true
      },
      {
        "Name": "conn",
        "Type": "System.String",
        "IsRequired": false
      },
      {
        "Name": "ip_address",
        "Type": "System.String",
        "IsRequired": false
      }
    ],
    "ReturnTypes": [
      {
        "Type": "System.Void",
        "MediaTypes": [],
        "StatusCode": 200
      }
    ]
  },
  {
    "ContainingType": "Converted_POS.FunctionController",
    "Method": "UpdateMainFunction",
    "RelativePath": "api/Function",
    "HttpMethod": "",
    "IsController": true,
    "Order": 0,
    "Parameters": [
      {
        "Name": "mainfunction_id",
        "Type": "System.Nullable\u00601[[System.Int32, System.Private.CoreLib, Version=9.0.0.0, Culture=neutral, PublicKeyToken=7cec85d7bea7798e]]",
        "IsRequired": false
      },
      {
        "Name": "func",
        "Type": "Converted_POS.Models.clsFunction",
        "IsRequired": true
      },
      {
        "Name": "conn",
        "Type": "System.String",
        "IsRequired": false
      },
      {
        "Name": "ip_address",
        "Type": "System.String",
        "IsRequired": false
      }
    ],
    "ReturnTypes": [
      {
        "Type": "System.Void",
        "MediaTypes": [],
        "StatusCode": 200
      }
    ]
  },
  {
    "ContainingType": "Converted_POS.FunctionController",
    "Method": "SaveUpdatedData",
    "RelativePath": "api/Function",
    "HttpMethod": "POST",
    "IsController": true,
    "Order": 0,
    "Parameters": [
      {
        "Name": "funcData",
        "Type": "Converted_POS.Models.clsFunction",
        "IsRequired": true
      }
    ],
    "ReturnTypes": []
  },
  {
    "ContainingType": "Converted_POS.FunctionController",
    "Method": "InsertFunctionDetails",
    "RelativePath": "api/Function",
    "HttpMethod": "",
    "IsController": true,
    "Order": 0,
    "Parameters": [
      {
        "Name": "func",
        "Type": "Converted_POS.Models.clsFunction",
        "IsRequired": true
      },
      {
        "Name": "conn",
        "Type": "System.String",
        "IsRequired": false
      },
      {
        "Name": "ip_address",
        "Type": "System.String",
        "IsRequired": false
      },
      {
        "Name": "buttonId",
        "Type": "System.String",
        "IsRequired": false
      },
      {
        "Name": "Function_Id",
        "Type": "System.Int32",
        "IsRequired": false
      }
    ],
    "ReturnTypes": [
      {
        "Type": "System.Void",
        "MediaTypes": [],
        "StatusCode": 200
      }
    ]
  },
  {
    "ContainingType": "Converted_POS.FunctionController",
    "Method": "updateFunctionDetails",
    "RelativePath": "api/Function",
    "HttpMethod": "",
    "IsController": true,
    "Order": 0,
    "Parameters": [
      {
        "Name": "func",
        "Type": "Converted_POS.Models.clsFunction",
        "IsRequired": true
      },
      {
        "Name": "conn",
        "Type": "System.String",
        "IsRequired": false
      },
      {
        "Name": "ip_address",
        "Type": "System.String",
        "IsRequired": false
      },
      {
        "Name": "Button_Id",
        "Type": "System.String",
        "IsRequired": false
      },
      {
        "Name": "Function_Id",
        "Type": "System.Int32",
        "IsRequired": false
      }
    ],
    "ReturnTypes": [
      {
        "Type": "System.Void",
        "MediaTypes": [],
        "StatusCode": 200
      }
    ]
  },
  {
    "ContainingType": "Converted_POS.FunctionController",
    "Method": "BindData",
    "RelativePath": "api/Function",
    "HttpMethod": "",
    "IsController": true,
    "Order": 0,
    "Parameters": [
      {
        "Name": "buttonId",
        "Type": "System.String",
        "IsRequired": false
      },
      {
        "Name": "name",
        "Type": "System.String",
        "IsRequired": false
      },
      {
        "Name": "for_color",
        "Type": "System.String",
        "IsRequired": false
      },
      {
        "Name": "back_color",
        "Type": "System.String",
        "IsRequired": false
      },
      {
        "Name": "is_active",
        "Type": "System.String",
        "IsRequired": false
      },
      {
        "Name": "big_button",
        "Type": "System.String",
        "IsRequired": false
      },
      {
        "Name": "Function_Id",
        "Type": "System.String",
        "IsRequired": false
      },
      {
        "Name": "Panel_Id",
        "Type": "System.String",
        "IsRequired": false
      },
      {
        "Name": "caption_type",
        "Type": "System.String",
        "IsRequired": false
      },
      {
        "Name": "item",
        "Type": "System.String",
        "IsRequired": false
      },
      {
        "Name": "Data_dt",
        "Type": "System.Data.DataTable",
        "IsRequired": true
      },
      {
        "Name": "namee",
        "Type": "System.String",
        "IsRequired": false
      },
      {
        "Name": "PlatformAdd",
        "Type": "System.String",
        "IsRequired": false
      },
      {
        "Name": "Dept_Id",
        "Type": "System.String",
        "IsRequired": false
      },
      {
        "Name": "Couse_Id",
        "Type": "System.String",
        "IsRequired": false
      },
      {
        "Name": "IsGroupByCourse",
        "Type": "System.Boolean",
        "IsRequired": false
      },
      {
        "Name": "IsGroupByDept",
        "Type": "System.Boolean",
        "IsRequired": false
      },
      {
        "Name": "ProfileId",
        "Type": "System.String",
        "IsRequired": false
      },
      {
        "Name": "DefaultDateTime",
        "Type": "System.String",
        "IsRequired": false
      },
      {
        "Name": "parentId",
        "Type": "System.String",
        "IsRequired": false
      }
    ],
    "ReturnTypes": [
      {
        "Type": "System.Data.DataTable",
        "MediaTypes": [
          "text/plain",
          "application/json",
          "text/json"
        ],
        "StatusCode": 200
      }
    ]
  },
  {
    "ContainingType": "Converted_POS.FunctionController",
    "Method": "DepSelect_By_Cmp",
    "RelativePath": "api/Function",
    "HttpMethod": "",
    "IsController": true,
    "Order": 0,
    "Parameters": [
      {
        "Name": "c_id",
        "Type": "System.Nullable\u00601[[System.Int32, System.Private.CoreLib, Version=9.0.0.0, Culture=neutral, PublicKeyToken=7cec85d7bea7798e]]",
        "IsRequired": false
      },
      {
        "Name": "conn",
        "Type": "System.String",
        "IsRequired": false
      }
    ],
    "ReturnTypes": [
      {
        "Type": "System.Collections.Generic.List\u00601[[Microsoft.AspNetCore.Mvc.Rendering.SelectListItem, Microsoft.AspNetCore.Mvc.ViewFeatures, Version=9.0.0.0, Culture=neutral, PublicKeyToken=adb9793829ddae60]]",
        "MediaTypes": [
          "text/plain",
          "application/json",
          "text/json"
        ],
        "StatusCode": 200
      }
    ]
  },
  {
    "ContainingType": "Converted_POS.FunctionController",
    "Method": "CourseSelect_By_Cmp",
    "RelativePath": "api/Function",
    "HttpMethod": "",
    "IsController": true,
    "Order": 0,
    "Parameters": [
      {
        "Name": "c_id",
        "Type": "System.Nullable\u00601[[System.Int32, System.Private.CoreLib, Version=9.0.0.0, Culture=neutral, PublicKeyToken=7cec85d7bea7798e]]",
        "IsRequired": false
      },
      {
        "Name": "conn",
        "Type": "System.String",
        "IsRequired": false
      }
    ],
    "ReturnTypes": [
      {
        "Type": "System.Collections.Generic.List\u00601[[Microsoft.AspNetCore.Mvc.Rendering.SelectListItem, Microsoft.AspNetCore.Mvc.ViewFeatures, Version=9.0.0.0, Culture=neutral, PublicKeyToken=adb9793829ddae60]]",
        "MediaTypes": [
          "text/plain",
          "application/json",
          "text/json"
        ],
        "StatusCode": 200
      }
    ]
  },
  {
    "ContainingType": "Converted_POS.FunctionController",
    "Method": "SelectProfile",
    "RelativePath": "api/Function",
    "HttpMethod": "",
    "IsController": true,
    "Order": 0,
    "Parameters": [
      {
        "Name": "c_id",
        "Type": "System.Nullable\u00601[[System.Int32, System.Private.CoreLib, Version=9.0.0.0, Culture=neutral, PublicKeyToken=7cec85d7bea7798e]]",
        "IsRequired": false
      },
      {
        "Name": "conn",
        "Type": "System.String",
        "IsRequired": false
      }
    ],
    "ReturnTypes": [
      {
        "Type": "System.Collections.Generic.List\u00601[[Microsoft.AspNetCore.Mvc.Rendering.SelectListItem, Microsoft.AspNetCore.Mvc.ViewFeatures, Version=9.0.0.0, Culture=neutral, PublicKeyToken=adb9793829ddae60]]",
        "MediaTypes": [
          "text/plain",
          "application/json",
          "text/json"
        ],
        "StatusCode": 200
      }
    ]
  },
  {
    "ContainingType": "Converted_POS.FunctionController",
    "Method": "SelectPricesByCmp",
    "RelativePath": "api/Function",
    "HttpMethod": "",
    "IsController": true,
    "Order": 0,
    "Parameters": [
      {
        "Name": "c_id",
        "Type": "System.Nullable\u00601[[System.Int32, System.Private.CoreLib, Version=9.0.0.0, Culture=neutral, PublicKeyToken=7cec85d7bea7798e]]",
        "IsRequired": false
      },
      {
        "Name": "conn",
        "Type": "System.String",
        "IsRequired": false
      }
    ],
    "ReturnTypes": [
      {
        "Type": "System.Collections.Generic.List\u00601[[Microsoft.AspNetCore.Mvc.Rendering.SelectListItem, Microsoft.AspNetCore.Mvc.ViewFeatures, Version=9.0.0.0, Culture=neutral, PublicKeyToken=adb9793829ddae60]]",
        "MediaTypes": [
          "text/plain",
          "application/json",
          "text/json"
        ],
        "StatusCode": 200
      }
    ]
  },
  {
    "ContainingType": "Converted_POS.FunctionController",
    "Method": "HandleButtonClick",
    "RelativePath": "api/Function/HandleButtonClick",
    "HttpMethod": "POST",
    "IsController": true,
    "Order": 0,
    "Parameters": [
      {
        "Name": "request",
        "Type": "Converted_POS.ButtonRequestModel",
        "IsRequired": true
      },
      {
        "Name": "additionalParameter",
        "Type": "System.String",
        "IsRequired": false
      }
    ],
    "ReturnTypes": []
  },
  {
    "ContainingType": "Converted_POS.FunctionController",
    "Method": "SelectedPanelChanged",
    "RelativePath": "api/Function/SelectedPanelChanged",
    "HttpMethod": "POST",
    "IsController": true,
    "Order": 0,
    "Parameters": [
      {
        "Name": "request",
        "Type": "Converted_POS.Models.clsFunction",
        "IsRequired": true
      }
    ],
    "ReturnTypes": []
  },
  {
    "ContainingType": "Converted_POS.Controllers.ProductReportController",
    "Method": "GetProductDetails",
    "RelativePath": "api/ProductReport/details",
    "HttpMethod": "GET",
    "IsController": true,
    "Order": 0,
    "Parameters": [
      {
        "Name": "productId",
        "Type": "System.Int32",
        "IsRequired": false
      },
      {
        "Name": "fromDate",
        "Type": "System.Nullable\u00601[[System.DateTime, System.Private.CoreLib, Version=9.0.0.0, Culture=neutral, PublicKeyToken=7cec85d7bea7798e]]",
        "IsRequired": false
      },
      {
        "Name": "toDate",
        "Type": "System.Nullable\u00601[[System.DateTime, System.Private.CoreLib, Version=9.0.0.0, Culture=neutral, PublicKeyToken=7cec85d7bea7798e]]",
        "IsRequired": false
      }
    ],
    "ReturnTypes": []
  },
  {
    "ContainingType": "Converted_POS.Controllers.ProductReportController",
    "Method": "ExportProductReport",
    "RelativePath": "api/ProductReport/export",
    "HttpMethod": "GET",
    "IsController": true,
    "Order": 0,
    "Parameters": [
      {
        "Name": "fromDate",
        "Type": "System.Nullable\u00601[[System.DateTime, System.Private.CoreLib, Version=9.0.0.0, Culture=neutral, PublicKeyToken=7cec85d7bea7798e]]",
        "IsRequired": false
      },
      {
        "Name": "toDate",
        "Type": "System.Nullable\u00601[[System.DateTime, System.Private.CoreLib, Version=9.0.0.0, Culture=neutral, PublicKeyToken=7cec85d7bea7798e]]",
        "IsRequired": false
      },
      {
        "Name": "productId",
        "Type": "System.Nullable\u00601[[System.Int32, System.Private.CoreLib, Version=9.0.0.0, Culture=neutral, PublicKeyToken=7cec85d7bea7798e]]",
        "IsRequired": false
      },
      {
        "Name": "categoryId",
        "Type": "System.Nullable\u00601[[System.Int32, System.Private.CoreLib, Version=9.0.0.0, Culture=neutral, PublicKeyToken=7cec85d7bea7798e]]",
        "IsRequired": false
      },
      {
        "Name": "duration",
        "Type": "System.String",
        "IsRequired": false
      },
      {
        "Name": "type",
        "Type": "System.String",
        "IsRequired": false
      }
    ],
    "ReturnTypes": []
  },
  {
    "ContainingType": "Converted_POS.Controllers.ProductReportController",
    "Method": "GetProductSummary",
    "RelativePath": "api/ProductReport/summary",
    "HttpMethod": "GET",
    "IsController": true,
    "Order": 0,
    "Parameters": [
      {
        "Name": "fromDate",
        "Type": "System.Nullable\u00601[[System.DateTime, System.Private.CoreLib, Version=9.0.0.0, Culture=neutral, PublicKeyToken=7cec85d7bea7798e]]",
        "IsRequired": false
      },
      {
        "Name": "toDate",
        "Type": "System.Nullable\u00601[[System.DateTime, System.Private.CoreLib, Version=9.0.0.0, Culture=neutral, PublicKeyToken=7cec85d7bea7798e]]",
        "IsRequired": false
      },
      {
        "Name": "productId",
        "Type": "System.Nullable\u00601[[System.Int32, System.Private.CoreLib, Version=9.0.0.0, Culture=neutral, PublicKeyToken=7cec85d7bea7798e]]",
        "IsRequired": false
      },
      {
        "Name": "categoryId",
        "Type": "System.Nullable\u00601[[System.Int32, System.Private.CoreLib, Version=9.0.0.0, Culture=neutral, PublicKeyToken=7cec85d7bea7798e]]",
        "IsRequired": false
      },
      {
        "Name": "duration",
        "Type": "System.String",
        "IsRequired": false
      },
      {
        "Name": "type",
        "Type": "System.String",
        "IsRequired": false
      },
      {
        "Name": "includeReturns",
        "Type": "System.Boolean",
        "IsRequired": false
      },
      {
        "Name": "locationId",
        "Type": "System.Nullable\u00601[[System.Int32, System.Private.CoreLib, Version=9.0.0.0, Culture=neutral, PublicKeyToken=7cec85d7bea7798e]]",
        "IsRequired": false
      },
      {
        "Name": "tillIds",
        "Type": "System.String",
        "IsRequired": false
      },
      {
        "Name": "customerId",
        "Type": "System.Nullable\u00601[[System.Int32, System.Private.CoreLib, Version=9.0.0.0, Culture=neutral, PublicKeyToken=7cec85d7bea7798e]]",
        "IsRequired": false
      }
    ],
    "ReturnTypes": []
  },
  {
    "ContainingType": "Converted_POS.WSController",
    "Method": "Index",
    "RelativePath": "WebService/MyWCFService",
    "HttpMethod": "",
    "IsController": true,
    "Order": 0,
    "Parameters": [],
    "ReturnTypes": []
  },
  {
    "ContainingType": "Converted_POS.WSController",
    "Method": "DataTable",
    "RelativePath": "WebService/MyWCFService",
    "HttpMethod": "GET",
    "IsController": true,
    "Order": 0,
    "Parameters": [
      {
        "Name": "dt",
        "Type": "System.Data.DataTable",
        "IsRequired": true
      }
    ],
    "ReturnTypes": [
      {
        "Type": "System.String",
        "MediaTypes": [
          "text/plain",
          "application/json",
          "text/json"
        ],
        "StatusCode": 200
      }
    ]
  },
  {
    "ContainingType": "Converted_POS.WSController",
    "Method": "DataTableToJsonWithEncoding",
    "RelativePath": "WebService/MyWCFService",
    "HttpMethod": "",
    "IsController": true,
    "Order": 0,
    "Parameters": [
      {
        "Name": "dt",
        "Type": "System.Data.DataTable",
        "IsRequired": true
      }
    ],
    "ReturnTypes": [
      {
        "Type": "System.String",
        "MediaTypes": [
          "text/plain",
          "application/json",
          "text/json"
        ],
        "StatusCode": 200
      }
    ]
  },
  {
    "ContainingType": "Converted_POS.WSController",
    "Method": "EncodeData",
    "RelativePath": "WebService/MyWCFService",
    "HttpMethod": "",
    "IsController": true,
    "Order": 0,
    "Parameters": [
      {
        "Name": "str",
        "Type": "System.String",
        "IsRequired": false
      }
    ],
    "ReturnTypes": [
      {
        "Type": "System.String",
        "MediaTypes": [
          "text/plain",
          "application/json",
          "text/json"
        ],
        "StatusCode": 200
      }
    ]
  },
  {
    "ContainingType": "Converted_POS.WSController",
    "Method": "DecodeData",
    "RelativePath": "WebService/MyWCFService",
    "HttpMethod": "",
    "IsController": true,
    "Order": 0,
    "Parameters": [
      {
        "Name": "str",
        "Type": "System.String",
        "IsRequired": false
      }
    ],
    "ReturnTypes": [
      {
        "Type": "System.String",
        "MediaTypes": [
          "text/plain",
          "application/json",
          "text/json"
        ],
        "StatusCode": 200
      }
    ]
  },
  {
    "ContainingType": "Converted_POS.WSController",
    "Method": "GetDataTableSp",
    "RelativePath": "WebService/MyWCFService",
    "HttpMethod": "",
    "IsController": true,
    "Order": 0,
    "Parameters": [
      {
        "Name": "spName",
        "Type": "System.String",
        "IsRequired": false
      },
      {
        "Name": "oColSqlparram",
        "Type": "Converted_POS.Models.ColSqlparram",
        "IsRequired": true
      },
      {
        "Name": "strTableName",
        "Type": "System.String",
        "IsRequired": false
      },
      {
        "Name": "constr",
        "Type": "System.String",
        "IsRequired": false
      }
    ],
    "ReturnTypes": [
      {
        "Type": "System.Data.DataTable",
        "MediaTypes": [
          "text/plain",
          "application/json",
          "text/json"
        ],
        "StatusCode": 200
      }
    ]
  },
  {
    "ContainingType": "Converted_POS.WSController",
    "Method": "ExecStoredProcedure",
    "RelativePath": "WebService/MyWCFService",
    "HttpMethod": "",
    "IsController": true,
    "Order": 0,
    "Parameters": [
      {
        "Name": "strProcedureName",
        "Type": "System.String",
        "IsRequired": false
      },
      {
        "Name": "oColSqlparram",
        "Type": "Converted_POS.Models.ColSqlparram",
        "IsRequired": true
      },
      {
        "Name": "constr",
        "Type": "System.String",
        "IsRequired": false
      }
    ],
    "ReturnTypes": [
      {
        "Type": "System.Void",
        "MediaTypes": [],
        "StatusCode": 200
      }
    ]
  },
  {
    "ContainingType": "Converted_POS.WSController",
    "Method": "CheckNull",
    "RelativePath": "WebService/MyWCFService",
    "HttpMethod": "",
    "IsController": true,
    "Order": 0,
    "Parameters": [
      {
        "Name": "vData",
        "Type": "System.Object",
        "IsRequired": true
      }
    ],
    "ReturnTypes": [
      {
        "Type": "System.String",
        "MediaTypes": [
          "text/plain",
          "application/json",
          "text/json"
        ],
        "StatusCode": 200
      }
    ]
  },
  {
    "ContainingType": "Converted_POS.WSController",
    "Method": "getStore",
    "RelativePath": "WebService/MyWCFService",
    "HttpMethod": "",
    "IsController": true,
    "Order": 0,
    "Parameters": [
      {
        "Name": "storeName",
        "Type": "System.String",
        "IsRequired": false
      }
    ],
    "ReturnTypes": [
      {
        "Type": "System.Data.DataTable",
        "MediaTypes": [
          "text/plain",
          "application/json",
          "text/json"
        ],
        "StatusCode": 200
      }
    ]
  },
  {
    "ContainingType": "Converted_POS.WSController",
    "Method": "Encrypt",
    "RelativePath": "WebService/MyWCFService",
    "HttpMethod": "",
    "IsController": true,
    "Order": 0,
    "Parameters": [
      {
        "Name": "clearText",
        "Type": "System.String",
        "IsRequired": false
      }
    ],
    "ReturnTypes": [
      {
        "Type": "System.String",
        "MediaTypes": [
          "text/plain",
          "application/json",
          "text/json"
        ],
        "StatusCode": 200
      }
    ]
  },
  {
    "ContainingType": "Converted_POS.WSController",
    "Method": "Decrypt",
    "RelativePath": "WebService/MyWCFService",
    "HttpMethod": "",
    "IsController": true,
    "Order": 0,
    "Parameters": [
      {
        "Name": "cipherText",
        "Type": "System.String",
        "IsRequired": false
      }
    ],
    "ReturnTypes": [
      {
        "Type": "System.String",
        "MediaTypes": [
          "text/plain",
          "application/json",
          "text/json"
        ],
        "StatusCode": 200
      }
    ]
  },
  {
    "ContainingType": "Converted_POS.WSController",
    "Method": "getconstr",
    "RelativePath": "WebService/MyWCFService",
    "HttpMethod": "",
    "IsController": true,
    "Order": 0,
    "Parameters": [
      {
        "Name": "dt",
        "Type": "System.Data.DataTable",
        "IsRequired": true
      }
    ],
    "ReturnTypes": [
      {
        "Type": "System.String",
        "MediaTypes": [
          "text/plain",
          "application/json",
          "text/json"
        ],
        "StatusCode": 200
      }
    ]
  },
  {
    "ContainingType": "Converted_POS.WSController",
    "Method": "AutoSync_List",
    "RelativePath": "WebService/MyWCFService/AutoSync_List",
    "HttpMethod": "GET",
    "IsController": true,
    "Order": 0,
    "Parameters": [
      {
        "Name": "authUsername",
        "Type": "System.String",
        "IsRequired": false
      },
      {
        "Name": "authPassword",
        "Type": "System.String",
        "IsRequired": false
      },
      {
        "Name": "Cmp_id",
        "Type": "System.Int32",
        "IsRequired": false
      },
      {
        "Name": "store_name",
        "Type": "System.String",
        "IsRequired": false
      },
      {
        "Name": "TillID",
        "Type": "System.Int32",
        "IsRequired": false
      }
    ],
    "ReturnTypes": [
      {
        "Type": "System.String",
        "MediaTypes": [
          "text/plain",
          "application/json",
          "text/json"
        ],
        "StatusCode": 200
      }
    ]
  },
  {
    "ContainingType": "Converted_POS.WSController",
    "Method": "AutoSync_Update",
    "RelativePath": "WebService/MyWCFService/AutoSync_Update",
    "HttpMethod": "GET",
    "IsController": true,
    "Order": 0,
    "Parameters": [
      {
        "Name": "authUsername",
        "Type": "System.String",
        "IsRequired": false
      },
      {
        "Name": "authPassword",
        "Type": "System.String",
        "IsRequired": false
      },
      {
        "Name": "Cmp_id",
        "Type": "System.Int32",
        "IsRequired": false
      },
      {
        "Name": "store_name",
        "Type": "System.String",
        "IsRequired": false
      },
      {
        "Name": "AutoSync_Id",
        "Type": "System.Int32",
        "IsRequired": false
      }
    ],
    "ReturnTypes": [
      {
        "Type": "System.String",
        "MediaTypes": [
          "text/plain",
          "application/json",
          "text/json"
        ],
        "StatusCode": 200
      }
    ]
  },
  {
    "ContainingType": "Converted_POS.WSController",
    "Method": "Customer_List",
    "RelativePath": "WebService/MyWCFService/Customer_List",
    "HttpMethod": "GET",
    "IsController": true,
    "Order": 0,
    "Parameters": [
      {
        "Name": "authUsername",
        "Type": "System.String",
        "IsRequired": false
      },
      {
        "Name": "authPassword",
        "Type": "System.String",
        "IsRequired": false
      },
      {
        "Name": "Cmp_id",
        "Type": "System.Int32",
        "IsRequired": false
      },
      {
        "Name": "store_name",
        "Type": "System.String",
        "IsRequired": false
      }
    ],
    "ReturnTypes": [
      {
        "Type": "System.String",
        "MediaTypes": [
          "text/plain",
          "application/json",
          "text/json"
        ],
        "StatusCode": 200
      }
    ]
  },
  {
    "ContainingType": "Converted_POS.WSController",
    "Method": "Graphic_Table",
    "RelativePath": "WebService/MyWCFService/Graphic_Table",
    "HttpMethod": "GET",
    "IsController": true,
    "Order": 0,
    "Parameters": [
      {
        "Name": "authUsername",
        "Type": "System.String",
        "IsRequired": false
      },
      {
        "Name": "authPassword",
        "Type": "System.String",
        "IsRequired": false
      },
      {
        "Name": "Cmp_id",
        "Type": "System.Int32",
        "IsRequired": false
      },
      {
        "Name": "store_name",
        "Type": "System.String",
        "IsRequired": false
      },
      {
        "Name": "location_id",
        "Type": "System.Int32",
        "IsRequired": false
      }
    ],
    "ReturnTypes": [
      {
        "Type": "System.String",
        "MediaTypes": [
          "text/plain",
          "application/json",
          "text/json"
        ],
        "StatusCode": 200
      }
    ]
  },
  {
    "ContainingType": "Converted_POS.WSController",
    "Method": "KioskSettiong_List",
    "RelativePath": "WebService/MyWCFService/KioskSettiong_List",
    "HttpMethod": "GET",
    "IsController": true,
    "Order": 0,
    "Parameters": [
      {
        "Name": "authUsername",
        "Type": "System.String",
        "IsRequired": false
      },
      {
        "Name": "authPassword",
        "Type": "System.String",
        "IsRequired": false
      },
      {
        "Name": "Cmp_id",
        "Type": "System.Int32",
        "IsRequired": false
      },
      {
        "Name": "store_name",
        "Type": "System.String",
        "IsRequired": false
      },
      {
        "Name": "TillID",
        "Type": "System.Int32",
        "IsRequired": false
      }
    ],
    "ReturnTypes": [
      {
        "Type": "System.String",
        "MediaTypes": [
          "text/plain",
          "application/json",
          "text/json"
        ],
        "StatusCode": 200
      }
    ]
  },
  {
    "ContainingType": "Converted_POS.WSController",
    "Method": "Schedule_List",
    "RelativePath": "WebService/MyWCFService/Schedule_List",
    "HttpMethod": "GET",
    "IsController": true,
    "Order": 0,
    "Parameters": [
      {
        "Name": "authUsername",
        "Type": "System.String",
        "IsRequired": false
      },
      {
        "Name": "authPassword",
        "Type": "System.String",
        "IsRequired": false
      },
      {
        "Name": "Cmp_id",
        "Type": "System.Int32",
        "IsRequired": false
      },
      {
        "Name": "store_name",
        "Type": "System.String",
        "IsRequired": false
      },
      {
        "Name": "location_id",
        "Type": "System.Int32",
        "IsRequired": false
      }
    ],
    "ReturnTypes": [
      {
        "Type": "System.String",
        "MediaTypes": [
          "text/plain",
          "application/json",
          "text/json"
        ],
        "StatusCode": 200
      }
    ]
  },
  {
    "ContainingType": "Converted_POS.WSController",
    "Method": "Login",
    "RelativePath": "WebService/MyWCFService/WebLogin",
    "HttpMethod": "GET",
    "IsController": true,
    "Order": 0,
    "Parameters": [
      {
        "Name": "authUsername",
        "Type": "System.String",
        "IsRequired": false
      },
      {
        "Name": "authPassword",
        "Type": "System.String",
        "IsRequired": false
      },
      {
        "Name": "user",
        "Type": "System.String",
        "IsRequired": false
      },
      {
        "Name": "pass",
        "Type": "System.String",
        "IsRequired": false
      },
      {
        "Name": "IP_Address",
        "Type": "System.String",
        "IsRequired": false
      },
      {
        "Name": "mac_id",
        "Type": "System.String",
        "IsRequired": false
      },
      {
        "Name": "store_name",
        "Type": "System.String",
        "IsRequired": false
      }
    ],
    "ReturnTypes": [
      {
        "Type": "System.String",
        "MediaTypes": [
          "text/plain",
          "application/json",
          "text/json"
        ],
        "StatusCode": 200
      }
    ]
  }
]